bldtool/__init__.py
bldtool/config/coveragerc
bldtool/config/pylintrc
bldtool/management/__init__.py
bldtool/management/commands/__init__.py
bldtool/management/commands/coverage.py
bldtool/management/commands/doc.py
bldtool/management/commands/lint.py
bldtool/management/commands/qc.py
bldtool/templates/bldtool/sphinx_conf.py
bldtool/templates/bldtool/sphinx_developer.rst
bldtool/templates/bldtool/sphinx_gitignore
bldtool/templates/bldtool/sphinx_user.rst
django_bldtool-0.0.1.dist-info/LICENSE
django_bldtool-0.0.1.dist-info/METADATA
django_bldtool-0.0.1.dist-info/WHEEL
django_bldtool-0.0.1.dist-info/top_level.txt
django_bldtool-0.0.1.dist-info/RECORD
