Metadata-Version: 2.1
Name: django-bldtool
Version: 0.0.1
Summary: UNKNOWN
Home-page: UNKNOWN
Author: Stefan Koch
Author-email: stefan.koch.micro@gmail.com
License: MIT Licence
Platform: UNKNOWN
Classifier: Environment :: Web Environment
Classifier: Framework :: Django
Classifier: Framework :: Django :: 3.0
Classifier: Intended Audience :: Developers
Classifier: License :: OSI Approved :: MIT License
Classifier: Operating System :: OS Independent
Classifier: Programming Language :: Python
Classifier: Programming Language :: Python :: 3.8
Classifier: Topic :: Internet :: WWW/HTTP
Classifier: Topic :: Internet :: WWW/HTTP :: Dynamic Content
Requires-Python: >=3.8
Requires-Dist: coverage
Requires-Dist: pylint
Requires-Dist: pylint-django
